eq_band_diagram.py
setup.py
eq_band_diagram.egg-info/PKG-INFO
eq_band_diagram.egg-info/SOURCES.txt
eq_band_diagram.egg-info/dependency_links.txt
eq_band_diagram.egg-info/top_level.txt