Metadata-Version: 1.1
Name: eq-band-diagram
Version: 0.1.0
Summary: Calculates equilibrium band diagrams for planar multilayer semiconductor structures.
Home-page: http://packages.python.org/eq_band_diagram
Author: Steven Byrnes
Author-email: steven.byrnes@gmail.com
License: MIT
Keywords: semiconductor physics,poisson equation,boltzmann equation,finite differences
Platform: UNKNOWN
Classifier: Development Status :: 4 - Beta
Classifier: Intended Audience :: Science/Research
Classifier: Topic :: Scientific/Engineering
Classifier: Topic :: Scientific/Engineering :: Physics
Classifier: License :: OSI Approved :: MIT License
Classifier: Operating System :: OS Independent
Classifier: Programming Language :: Python :: 2
